wmul_rivendell_tcp_client/__init__.py
wmul_rivendell_tcp_client/cli.py
wmul_rivendell_tcp_client/receiver.py
wmul_rivendell_tcp_client/song.py
wmul_rivendell_tcp_client-0.0.3.dist-info/entry_points.txt
wmul_rivendell_tcp_client-0.0.3.dist-info/licenses/LICENSE
wmul_rivendell_tcp_client-0.0.3.dist-info/WHEEL
wmul_rivendell_tcp_client-0.0.3.dist-info/METADATA
wmul_rivendell_tcp_client-0.0.3.dist-info/RECORD
