Metadata-Version: 2.4
Name: wmul_rivendell_tcp_client
Version: 0.0.3
Summary: TCP Client for Receiving 'Now Playing' information from Rivendell.
Author-email: Michael Stanley <stanley50@marshall.edu>
Classifier: Programming Language :: Python :: 3
Classifier: License :: OSI Approved :: MIT License
Classifier: Operating System :: OS Independent
Classifier: Development Status :: 5 - Production/Stable
License-File: LICENSE
Requires-Dist: wmul_logger>=0.6.0
Requires-Dist: wmul_emailer>=0.6.0
Requires-Dist: click
Requires-Dist: pytest ; extra == "test"
Requires-Dist: tox ; extra == "tox"
Project-URL: Bug Tracker, https://github.com/MikeTheHammer/wmul_rivendell_tcp_client/issues
Project-URL: Home, https://github.com/MikeTheHammer/wmul_rivendell_tcp_client
Provides-Extra: test
Provides-Extra: tox
